base_dag/__init__.py
base_dag/__main__.py
base_dag/dag.py
base_dag-0.1.10.dist-info/METADATA
base_dag-0.1.10.dist-info/WHEEL
base_dag-0.1.10.dist-info/RECORD
