Metadata-Version: 2.4
Name: base-dag
Version: 0.1.10
Summary: A simple base implementation of a Directed Acyclic Graph, intended to be subclassed for more specific functionality.
Project-URL: homepage, https://github.com/ResearchOS/base-dag
Project-URL: repository, https://github.com/ResearchOS/base-dag
Project-URL: documentation, https://github.com/ResearchOS/base-dag
Author-email: Mitchell Tillman <mtillman14@gmail.com>
Keywords: DAG,data structures,directed acyclic graph,graph
